LICENSE
setup.py
adjuster/__init__.py
adjuster/__main__.py
adjuster.egg-info/PKG-INFO
adjuster.egg-info/SOURCES.txt
adjuster.egg-info/dependency_links.txt
adjuster.egg-info/entry_points.txt
adjuster.egg-info/requires.txt
adjuster.egg-info/top_level.txt