Metadata-Version: 2.1
Name: adjuster
Version: 3.245
Summary: the Web Adjuster domain-rewriting proxy
Home-page: http://ssb22.user.srcf.net/adjuster/
Author: Silas S. Brown
Author-email: ssb22@cam.ac.uk
License: Apache 2
Platform: any
Classifier: Programming Language :: Python :: 2
Classifier: Programming Language :: Python :: 3
Classifier: License :: OSI Approved :: Apache Software License
Classifier: Operating System :: OS Independent
Requires-Python: >=2.5
License-File: LICENSE
